squishtest-2013.1.data/purelib/squishtest/Qt5ConcurrentSquish.dll
squishtest-2013.1.data/purelib/squishtest/Qt5CoreSquish.dll
squishtest-2013.1.data/purelib/squishtest/Qt5GuiSquish.dll
squishtest-2013.1.data/purelib/squishtest/Qt5NetworkSquish.dll
squishtest-2013.1.data/purelib/squishtest/Qt5SerialBusSquish.dll
squishtest-2013.1.data/purelib/squishtest/Qt5SerialPortSquish.dll
squishtest-2013.1.data/purelib/squishtest/Qt5SqlSquish.dll
squishtest-2013.1.data/purelib/squishtest/Qt5WebSocketsSquish.dll
squishtest-2013.1.data/purelib/squishtest/Qt5WidgetsSquish.dll
squishtest-2013.1.data/purelib/squishtest/Qt5XmlSquish.dll
squishtest-2013.1.data/purelib/squishtest/__init__.py
squishtest-2013.1.data/purelib/squishtest/algorithms.dll
squishtest-2013.1.data/purelib/squishtest/avcodecSquish-58.dll
squishtest-2013.1.data/purelib/squishtest/avformatSquish-58.dll
squishtest-2013.1.data/purelib/squishtest/avutilSquish-56.dll
squishtest-2013.1.data/purelib/squishtest/dialogapihook64.dll
squishtest-2013.1.data/purelib/squishtest/fkit.dll
squishtest-2013.1.data/purelib/squishtest/fmilib_shared.dll
squishtest-2013.1.data/purelib/squishtest/gherkin.dll
squishtest-2013.1.data/purelib/squishtest/libclangSquish.dll
squishtest-2013.1.data/purelib/squishtest/libmysql.dll
squishtest-2013.1.data/purelib/squishtest/libpq.dll
squishtest-2013.1.data/purelib/squishtest/msvcp140.dll
squishtest-2013.1.data/purelib/squishtest/squishdialoghook64.dll
squishtest-2013.1.data/purelib/squishtest/squishhook.dll
squishtest-2013.1.data/purelib/squishtest/squishinterpreter.dll
squishtest-2013.1.data/purelib/squishtest/squishjavascript.dll
squishtest-2013.1.data/purelib/squishtest/squishkjs.dll
squishtest-2013.1.data/purelib/squishtest/squishobjectmodel.dll
squishtest-2013.1.data/purelib/squishtest/squishperl.dll
squishtest-2013.1.data/purelib/squishtest/squishpython-2.7.dll
squishtest-2013.1.data/purelib/squishtest/squishpython-3.10.dll
squishtest-2013.1.data/purelib/squishtest/squishqtquickcommon.dll
squishtest-2013.1.dist-info/METADATA
squishtest-2013.1.dist-info/WHEEL
squishtest-2013.1.dist-info/top_level.txt
squishtest-2013.1.dist-info/RECORD
