Metadata-Version: 2.1
Name: squishtest
Version: 2013.1
Summary: Dynamsoft Barcode Reader Python project
Home-page: https://www.dynamsoft.com/Products/Dynamic-Barcode-Reader.aspx
Author: Dynamsoft
Author-email: support@dynamsoft.com
License: https://www.dynamsoft.com/Products/barcode-reader-license-agreement.aspx
Keywords: barcode DataMatrix QRCode 1D PDF417
Platform: UNKNOWN
Classifier: Development Status :: 5 - Production/Stable
Classifier: Intended Audience :: Developers
Classifier: Topic :: Software Development :: Libraries
Classifier: License :: Other/Proprietary License
Classifier: Programming Language :: Python :: 3.10
